inka2/__init__.py
inka2/__main__.py
inka2/cli.py
inka2/exceptions.py
inka2/helpers.py
inka2/mistune_plugins/__init__.py
inka2/mistune_plugins/mathjax.py
inka2/mistune_plugins/mathjax3.py
inka2/models/__init__.py
inka2/models/anki_api.py
inka2/models/anki_media.py
inka2/models/config.py
inka2/models/converter.py
inka2/models/hasher.py
inka2/models/highlighter.py
inka2/models/img_handler.py
inka2/models/parser.py
inka2/models/writer.py
inka2/models/notes/__init__.py
inka2/models/notes/basic_note.py
inka2/models/notes/cloze_note.py
inka2/models/notes/note.py
inka2-3.2.2.dist-info/licenses/LICENSE
inka2-3.2.2.dist-info/METADATA
inka2-3.2.2.dist-info/WHEEL
inka2-3.2.2.dist-info/entry_points.txt
inka2-3.2.2.dist-info/top_level.txt
inka2-3.2.2.dist-info/RECORD
