Metadata-Version: 2.4
Name: inka2
Version: 3.2.2
Summary: Command-line tool for adding flashcards from Markdown files to Anki
Author-email: sysid <sysid@gmx.de>, Kirill Salnikov <salnikov.k54@gmail.com>
License-Expression: GPL-3.0-only
Project-URL: Source, https://github.com/sysid/inka2
Project-URL: Documentation, https://github.com/sysid/inka2/wiki/Creating-cards
Classifier: Development Status :: 5 - Production/Stable
Classifier: Operating System :: OS Independent
Classifier: Intended Audience :: Education
Classifier: Topic :: Education :: Computer Aided Instruction (CAI)
Classifier: Topic :: Text Processing :: Markup :: Markdown
Classifier: Programming Language :: Python :: 3
Classifier: Programming Language :: Python :: 3.10
Classifier: Programming Language :: Python :: 3.11
Classifier: Programming Language :: Python :: 3.12
Classifier: Programming Language :: Python :: 3 :: Only
Requires-Python: >=3.10
License-File: LICENSE
Requires-Dist: anki>=24.11
Requires-Dist: aqt>=24.11
Requires-Dist: click>=8.1.8
Requires-Dist: isort>=5.13.2
Requires-Dist: mistune>=3.1.4
Requires-Dist: mypy>=1.14.1
Requires-Dist: pillow>=11.1.0
Requires-Dist: pyqt6>=6.8.0
Requires-Dist: pyqt6-webengine>=6.8.0
Requires-Dist: requests>=2.32.3
Requires-Dist: rich>=13.9.4
Dynamic: license-file
